aio9p/__init__.py
aio9p/constant.py
aio9p/dialect/Py9P2000.py
aio9p/dialect/Py9P2000u.py
aio9p/dialect/__init__.py
aio9p/dialect/client/Py9P2000.py
aio9p/dialect/client/Py9P2000u.py
aio9p/dialect/client/__init__.py
aio9p/example/__init__.py
aio9p/example/simple.py
aio9p/example/simple_u.py
aio9p/helper.py
aio9p/protocol.py
aio9p/stat.py
aio9p-0.3.3.dist-info/LICENSE
aio9p-0.3.3.dist-info/WHEEL
aio9p-0.3.3.dist-info/METADATA
aio9p-0.3.3.dist-info/RECORD
