Metadata-Version: 2.1
Name: aio9p
Version: 0.3.3
Summary: 
License: AGPL-3.0-or-later
Author: florpe
Author-email: jens.krewald@gmail.com
Requires-Python: >=3.10,<4.0
Classifier: License :: OSI Approved :: GNU Affero General Public License v3 or later (AGPLv3+)
Classifier: Programming Language :: Python :: 3
Classifier: Programming Language :: Python :: 3.10
Classifier: Programming Language :: Python :: 3.11
